setup.py
itable/__init__.py
itable/itable.py
itable.egg-info/PKG-INFO
itable.egg-info/SOURCES.txt
itable.egg-info/dependency_links.txt
itable.egg-info/requires.txt
itable.egg-info/top_level.txt