Metadata-Version: 1.0
Name: itable
Version: 0.0.1
Summary: View pretty tables in IPython
Home-page: http://github.com/mgymrek/itable
Author: Melissa Gymrek
Author-email: mgymrek@mit.edu
License: MIT
Download-URL: http://github.com/mgymrek/itable
Platform: UNKNOWN
Classifier: Development Status :: 4 - Beta
Classifier: Programming Language :: Python :: 2.6
Classifier: License :: OSI Approved :: MIT License
Classifier: Operating System :: OS Independent
Classifier: Topic :: Scientific/Engineering :: Visualization
